[[{"id": "64b9bca8f97880bb2dab3200", "value": 0.0033032567049808424, "date": "2023-07-20T23:00:00.000Z", "stationId": 230, "code": "PM2.5", "unit": "mg/m3"}], [{"id": "64b9bca8f97880bb2dab3280", "value": 0.0007994081503733772, "date": "2023-07-20T23:00:00.000Z", "stationId": 107, "code": "PM2.5", "unit": "mg/m3"}], [{"id": "64b9bca8f97880bb2dab32e3", "value": 0.04921576782106782, "date": "2023-07-20T23:00:00.000Z", "stationId": 58, "code": "PM2.5", "unit": "mg/m3"}], [{"id": "64b9bca8f97880bb2dab32f2", "value": 0.016736666666666667, "date": "2023-07-20T23:00:00.000Z", "stationId": 60, "code": "PM2.5", "unit": "mg/m3"}], [{"id": "64b9bca8f97880bb2dab3300", "value": 0.010663502176527178, "date": "2023-07-20T23:00:00.000Z", "stationId": 56, "code": "PM2.5", "unit": "mg/m3"}], [{"id": "64b9bca8f97880bb2dab3700", "value": 0.0013013333333333334, "date": "2023-07-20T23:00:00.000Z", "stationId": 28, "code": "PM2.5", "unit": "mg/m3"}], [{"id": "64b9bca8f97880bb2dab3754", "value": 0.002657, "date": "2023-07-20T23:00:00.000Z", "stationId": 97, "code": "PM2.5", "unit": "mg/m3"}], [{"id": "64b9bca8f97880bb2dab376c", "value": 0.0015595000000000001, "date": "2023-07-20T23:00:00.000Z", "stationId": 59, "code": "PM2.5", "unit": "mg/m3"}], [{"id": "64b9bca8f97880bb2dab37a8", "value": 0.0011656666666666666, "date": "2023-07-20T23:00:00.000Z", "stationId": 57, "code": "PM2.5", "unit": "mg/m3"}], [{"id": "64b9bca8f97880bb2dab3914", "value": 0.001478666666666667, "date": "2023-07-20T23:00:00.000Z", "stationId": 39, "code": "PM2.5", "unit": "mg/m3"}], [{"id": "64b9bca8f97880bb2dab3922", "value": 0.006913000000000001, "date": "2023-07-20T23:00:00.000Z", "stationId": 27, "code": "PM2.5", "unit": "mg/m3"}], [{"id": "64b9bca8f97880bb2dab3988", "value": 0.008542000000000001, "date": "2023-07-20T23:00:00.000Z", "stationId": 25, "code": "PM2.5", "unit": "mg/m3"}], [{"id": "64b9bca8f97880bb2dab39ab", "value": 0.0035545000000000004, "date": "2023-07-20T23:00:00.000Z", "stationId": 26, "code": "PM2.5", "unit": "mg/m3"}]]