[[{"id": "64d0eb14f97880bb2d5da3f9", "value": 0.003131713688610241, "date": "2023-08-07T13:00:00.000Z", "stationId": 230, "code": "PM2.5", "unit": "mg/m3"}], [{"id": "64d0eb14f97880bb2d5da479", "value": 0.0001554806892031179, "date": "2023-08-07T13:00:00.000Z", "stationId": 107, "code": "PM2.5", "unit": "mg/m3"}], [{"id": "64d0eb14f97880bb2d5da549", "value": 0.011644971590909093, "date": "2023-08-07T13:00:00.000Z", "stationId": 58, "code": "PM2.5", "unit": "mg/m3"}], [{"id": "64d0eb14f97880bb2d5da557", "value": 0.0103935, "date": "2023-08-07T13:00:00.000Z", "stationId": 60, "code": "PM2.5", "unit": "mg/m3"}], [{"id": "64d0eb14f97880bb2d5da56b", "value": 0.01495860037878788, "date": "2023-08-07T13:00:00.000Z", "stationId": 56, "code": "PM2.5", "unit": "mg/m3"}], [{"id": "64d0eb14f97880bb2d5dac6a", "value": 0.0202905, "date": "2023-08-07T13:00:00.000Z", "stationId": 28, "code": "PM2.5", "unit": "mg/m3"}], [{"id": "64d0eb14f97880bb2d5dacc3", "value": 0.0027530000000000002, "date": "2023-08-07T13:00:00.000Z", "stationId": 97, "code": "PM2.5", "unit": "mg/m3"}], [{"id": "64d0eb14f97880bb2d5dacdb", "value": 0.0021425, "date": "2023-08-07T13:00:00.000Z", "stationId": 59, "code": "PM2.5", "unit": "mg/m3"}], [{"id": "64d0eb14f97880bb2d5dad14", "value": 0.001074, "date": "2023-08-07T13:00:00.000Z", "stationId": 57, "code": "PM2.5", "unit": "mg/m3"}], [{"id": "64d0eb15f97880bb2d5dae84", "value": 0.001532, "date": "2023-08-07T13:00:00.000Z", "stationId": 39, "code": "PM2.5", "unit": "mg/m3"}], [{"id": "64d0eb15f97880bb2d5dae93", "value": 0.0045555000000000005, "date": "2023-08-07T13:00:00.000Z", "stationId": 27, "code": "PM2.5", "unit": "mg/m3"}], [{"id": "64d0eb15f97880bb2d5daed6", "value": 0.006947999999999999, "date": "2023-08-07T13:00:00.000Z", "stationId": 25, "code": "PM2.5", "unit": "mg/m3"}], [{"id": "64d0eb15f97880bb2d5daef9", "value": 0.0031114999999999997, "date": "2023-08-07T13:00:00.000Z", "stationId": 26, "code": "PM2.5", "unit": "mg/m3"}]]