[[{"id": "67f1b5f9a69d8c6bcdf54301", "value": 0.0028555555555555556, "date": "2025-04-05T23:00:00.000Z", "stationId": 230, "code": "PM2.5", "unit": "mg/m3"}], [{"id": "67f1b5f9a69d8c6bcdf54408", "value": 0, "date": "2025-04-05T23:00:00.000Z", "stationId": 58, "code": "PM2.5", "unit": "mg/m3"}], [{"id": "67f1b5f9a69d8c6bcdf54422", "value": 0, "date": "2025-04-05T23:00:00.000Z", "stationId": 56, "code": "PM2.5", "unit": "mg/m3"}], [{"id": "67f1b5f9a69d8c6bcdf547b8", "value": 0, "date": "2025-04-05T23:00:00.000Z", "stationId": 28, "code": "PM2.5", "unit": "mg/m3"}], [{"id": "67f1b5f9a69d8c6bcdf54801", "value": 0.019478333333333334, "date": "2025-04-05T23:00:00.000Z", "stationId": 59, "code": "PM2.5", "unit": "mg/m3"}], [{"id": "67f1b5f9a69d8c6bcdf54836", "value": 0.0010176666666666667, "date": "2025-04-05T23:00:00.000Z", "stationId": 57, "code": "PM2.5", "unit": "mg/m3"}], [{"id": "67f1b5faa69d8c6bcdf54961", "value": 0.0015233333333333334, "date": "2025-04-05T23:00:00.000Z", "stationId": 39, "code": "PM2.5", "unit": "mg/m3"}], [{"id": "67f1b5faa69d8c6bcdf54970", "value": 0.0017356666666666666, "date": "2025-04-05T23:00:00.000Z", "stationId": 27, "code": "PM2.5", "unit": "mg/m3"}], [{"id": "67f1b5faa69d8c6bcdf549f0", "value": 0.007257666666666667, "date": "2025-04-05T23:00:00.000Z", "stationId": 26, "code": "PM2.5", "unit": "mg/m3"}], [{"id": "67f1b803a69d8c6bcdf63c27", "value": 0.012296333333333333, "date": "2025-04-05T23:00:00.000Z", "stationId": 97, "code": "PM2.5", "unit": "mg/m3"}]]