[[{"id": "65144395f97880bb2df2221f", "value": 0.06721581035923141, "date": "2023-09-27T15:00:00.000Z", "stationId": 230, "code": "PM2.5", "unit": "mg/m3"}], [{"id": "65144395f97880bb2df2234d", "value": 0.02159, "date": "2023-09-27T15:00:00.000Z", "stationId": 60, "code": "PM2.5", "unit": "mg/m3"}], [{"id": "65144395f97880bb2df2235d", "value": 0, "date": "2023-09-27T15:00:00.000Z", "stationId": 56, "code": "PM2.5", "unit": "mg/m3"}], [{"id": "65144396f97880bb2df229aa", "value": 0.0007513333333333333, "date": "2023-09-27T15:00:00.000Z", "stationId": 28, "code": "PM2.5", "unit": "mg/m3"}], [{"id": "65144396f97880bb2df229f0", "value": 0.000433, "date": "2023-09-27T15:00:00.000Z", "stationId": 97, "code": "PM2.5", "unit": "mg/m3"}], [{"id": "65144396f97880bb2df22a08", "value": 0.001983, "date": "2023-09-27T15:00:00.000Z", "stationId": 59, "code": "PM2.5", "unit": "mg/m3"}], [{"id": "65144396f97880bb2df22b90", "value": 0.008636, "date": "2023-09-27T15:00:00.000Z", "stationId": 27, "code": "PM2.5", "unit": "mg/m3"}], [{"id": "65144396f97880bb2df22be5", "value": 0.0006406666666666667, "date": "2023-09-27T15:00:00.000Z", "stationId": 25, "code": "PM2.5", "unit": "mg/m3"}], [{"id": "65144396f97880bb2df22bfb", "value": 0.008177, "date": "2023-09-27T15:00:00.000Z", "stationId": 26, "code": "PM2.5", "unit": "mg/m3"}]]