{
  "displayFieldName" : "",
  "fieldAliases" : {
    "OBJECTID_1" : "OBJECTID_1",
    "Time" : "Time",
    "Shape_Length" : "Shape_Length"
  },
  "geometryType" : "esriGeometryPolyline",
  "spatialReference" : {
    "wkid" : 4326,
    "latestWkid" : 4326
  },
  "fields" : [
    {
      "name" : "OBJECTID_1",
      "type" : "esriFieldTypeOID",
      "alias" : "OBJECTID_1"
    },
    {
      "name" : "Time",
      "type" : "esriFieldTypeSmallInteger",
      "alias" : "Time"
    },
    {
      "name" : "Shape_Length",
      "type" : "esriFieldTypeDouble",
      "alias" : "Shape_Length"
    }
  ],
  "features" : [
    {
      "attributes" : {
        "OBJECTID_1" : 1,
        "Time" : 203,
        "Shape_Length" : 0.0024339237868420522
      },
      "geometry" : {
        "paths" : [
          [
            [
              76.828648000000044,
              43.243424000000061
            ],
            [
              76.830996000000084,
              43.244065000000035
            ]
          ]
        ]
      }
    },
    {
      "attributes" : {
        "OBJECTID_1" : 2,
        "Time" : 163,
        "Shape_Length" : 0.0019403342495379226
      },
      "geometry" : {
        "paths" : [
          [
            [
              76.830996000000084,
              43.244065000000035
            ],
            [
              76.832875000000058,
              43.244549000000063
            ]
          ]
        ]
      }
    },
    {
      "attributes" : {
        "OBJECTID_1" : 3,
        "Time" : 261,
        "Shape_Length" : 0.0031083431277766304
      },
      "geometry" : {
        "paths" : [
          [
            [
              76.832875000000058,
              43.244549000000063
            ],
            [
              76.835866000000067,
              43.24539500000003
            ]
          ]
        ]
      }
    },
    {
      "attributes" : {
        "OBJECTID_1" : 4,
        "Time" : 191,
        "Shape_Length" : 0.0022318624509524618
      },
      "geometry" : {
        "paths" : [
          [
            [
              76.835866000000067,
              43.24539500000003
            ],
            [
              76.837967000000049,
              43.246148000000062
            ]
          ]
        ]
      }
    },
    {
      "attributes" : {
        "OBJECTID_1" : 5,
        "Time" : 180,
        "Shape_Length" : 0.0021272717268708699
      },
      "geometry" : {
        "paths" : [
          [
            [
              76.837967000000049,
              43.246148000000062
            ],
            [
              76.840001000000029,
              43.246771000000081
            ]
          ]
        ]
      }
    },
    {
      "attributes" : {
        "OBJECTID_1" : 6,
        "Time" : 242,
        "Shape_Length" : 0.0028104634849480548
      },
      "geometry" : {
        "paths" : [
          [
            [
              76.840001000000029,
              43.246771000000081
            ],
            [
              76.842594000000076,
              43.247855000000072
            ]
          ]
        ]
      }
    },
    {
      "attributes" : {
        "OBJECTID_1" : 7,
        "Time" : 192,
        "Shape_Length" : 0.0022070781589889586
      },
      "geometry" : {
        "paths" : [
          [
            [
              76.842594000000076,
              43.247855000000072
            ],
            [
              76.844607000000053,
              43.248760000000061
            ]
          ]
        ]
      }
    },
    {
      "attributes" : {
        "OBJECTID_1" : 8,
        "Time" : 205,
        "Shape_Length" : 0.0024077881966799428
      },
      "geometry" : {
        "paths" : [
          [
            [
              76.844607000000053,
              43.248760000000061
            ],
            [
              76.846895000000075,
              43.249510000000043
            ]
          ]
        ]
      }
    },
    {
      "attributes" : {
        "OBJECTID_1" : 9,
        "Time" : 272,
        "Shape_Length" : 0.0032815382063634516
      },
      "geometry" : {
        "paths" : [
          [
            [
              76.846895000000075,
              43.249510000000043
            ],
            [
              76.850082000000043,
              43.250292000000059
            ]
          ]
        ]
      }
    },
    {
      "attributes" : {
        "OBJECTID_1" : 10,
        "Time" : 268,
        "Shape_Length" : 0.0032365050594739108
      },
      "geometry" : {
        "paths" : [
          [
            [
              76.850082000000043,
              43.250292000000059
            ],
            [
              76.853256000000044,
              43.250925000000052
            ]
          ]
        ]
      }
    },
    {
      "attributes" : {
        "OBJECTID_1" : 11,
        "Time" : 293,
        "Shape_Length" : 0.0035097249180286406
      },
      "geometry" : {
        "paths" : [
          [
            [
              76.853256000000044,
              43.250925000000052
            ],
            [
              76.856643000000076,
              43.25184500000006
            ]
          ]
        ]
      }
    },
    {
      "attributes" : {
        "OBJECTID_1" : 12,
        "Time" : 142,
        "Shape_Length" : 0.0016811811324162816
      },
      "geometry" : {
        "paths" : [
          [
            [
              76.856643000000076,
              43.25184500000006
            ],
            [
              76.85824400000007,
              43.252358000000072
            ]
          ]
        ]
      }
    },
    {
      "attributes" : {
        "OBJECTID_1" : 13,
        "Time" : 168,
        "Shape_Length" : 0.0018812976904348509
      },
      "geometry" : {
        "paths" : [
          [
            [
              76.85824400000007,
              43.252358000000072
            ],
            [
              76.859885000000077,
              43.25327800000008
            ]
          ]
        ]
      }
    },
    {
      "attributes" : {
        "OBJECTID_1" : 14,
        "Time" : 191,
        "Shape_Length" : 0.0020671265079828679
      },
      "geometry" : {
        "paths" : [
          [
            [
              76.859885000000077,
              43.25327800000008
            ],
            [
              76.861571000000083,
              43.254474000000073
            ]
          ]
        ]
      }
    },
    {
      "attributes" : {
        "OBJECTID_1" : 15,
        "Time" : 190,
        "Shape_Length" : 0.0020730424501207165
      },
      "geometry" : {
        "paths" : [
          [
            [
              76.861571000000083,
              43.254474000000073
            ],
            [
              76.863283000000081,
              43.255643000000077
            ]
          ]
        ]
      }
    },
    {
      "attributes" : {
        "OBJECTID_1" : 16,
        "Time" : 180,
        "Shape_Length" : 0.0020322096348346784
      },
      "geometry" : {
        "paths" : [
          [
            [
              76.863283000000081,
              43.255643000000077
            ],
            [
              76.865093000000059,
              43.256567000000075
            ]
          ]
        ]
      }
    },
    {
      "attributes" : {
        "OBJECTID_1" : 17,
        "Time" : 153,
        "Shape_Length" : 0.0018016217694239143
      },
      "geometry" : {
        "paths" : [
          [
            [
              76.865093000000059,
              43.256567000000075
            ],
            [
              76.866797000000076,
              43.257152000000076
            ]
          ]
        ]
      }
    },
    {
      "attributes" : {
        "OBJECTID_1" : 18,
        "Time" : 226,
        "Shape_Length" : 0.0027047656090648858
      },
      "geometry" : {
        "paths" : [
          [
            [
              76.866797000000076,
              43.257152000000076
            ],
            [
              76.869408000000078,
              43.257858000000056
            ]
          ]
        ]
      }
    },
    {
      "attributes" : {
        "OBJECTID_1" : 19,
        "Time" : 273,
        "Shape_Length" : 0.0033488400976680885
      },
      "geometry" : {
        "paths" : [
          [
            [
              76.869408000000078,
              43.257858000000056
            ],
            [
              76.872755000000041,
              43.25796900000006
            ]
          ]
        ]
      }
    },
    {
      "attributes" : {
        "OBJECTID_1" : 20,
        "Time" : 339,
        "Shape_Length" : 0.0041734391094206801
      },
      "geometry" : {
        "paths" : [
          [
            [
              76.872755000000041,
              43.25796900000006
            ],
            [
              76.876918000000046,
              43.257674000000065
            ]
          ]
        ]
      }
    },
    {
      "attributes" : {
        "OBJECTID_1" : 21,
        "Time" : 163,
        "Shape_Length" : 0.0020049650869828095
      },
      "geometry" : {
        "paths" : [
          [
            [
              76.876918000000046,
              43.257674000000065
            ],
            [
              76.878920000000051,
              43.257565000000056
            ]
          ]
        ]
      }
    },
    {
      "attributes" : {
        "OBJECTID_1" : 22,
        "Time" : 133,
        "Shape_Length" : 0.0016373307546317269
      },
      "geometry" : {
        "paths" : [
          [
            [
              76.878920000000051,
              43.257565000000056
            ],
            [
              76.88055600000007,
              43.257499000000053
            ]
          ]
        ]
      }
    },
    {
      "attributes" : {
        "OBJECTID_1" : 23,
        "Time" : 130,
        "Shape_Length" : 0.0016040797985001139
      },
      "geometry" : {
        "paths" : [
          [
            [
              76.88055600000007,
              43.257499000000053
            ],
            [
              76.882160000000056,
              43.257515000000069
            ]
          ]
        ]
      }
    },
    {
      "attributes" : {
        "OBJECTID_1" : 24,
        "Time" : 333,
        "Shape_Length" : 0.0039571234501497065
      },
      "geometry" : {
        "paths" : [
          [
            [
              76.882160000000056,
              43.257515000000069
            ],
            [
              76.88597500000003,
              43.25856600000003
            ]
          ]
        ]
      }
    },
    {
      "attributes" : {
        "OBJECTID_1" : 25,
        "Time" : 330,
        "Shape_Length" : 0.0039079675024616765
      },
      "geometry" : {
        "paths" : [
          [
            [
              76.88597500000003,
              43.25856600000003
            ],
            [
              76.88967800000006,
              43.25981500000006
            ]
          ]
        ]
      }
    },
    {
      "attributes" : {
        "OBJECTID_1" : 26,
        "Time" : 269,
        "Shape_Length" : 0.0031800091194900725
      },
      "geometry" : {
        "paths" : [
          [
            [
              76.88967800000006,
              43.25981500000006
            ],
            [
              76.89269100000007,
              43.26083200000005
            ]
          ]
        ]
      }
    },
    {
      "attributes" : {
        "OBJECTID_1" : 27,
        "Time" : 220,
        "Shape_Length" : 0.0025800748050766901
      },
      "geometry" : {
        "paths" : [
          [
            [
              76.89269100000007,
              43.26083200000005
            ],
            [
              76.89511600000003,
              43.261713000000043
            ]
          ]
        ]
      }
    },
    {
      "attributes" : {
        "OBJECTID_1" : 28,
        "Time" : 203,
        "Shape_Length" : 0.0023928230189812672
      },
      "geometry" : {
        "paths" : [
          [
            [
              76.89511600000003,
              43.261713000000043
            ],
            [
              76.897375000000068,
              43.26250200000004
            ]
          ]
        ]
      }
    },
    {
      "attributes" : {
        "OBJECTID_1" : 29,
        "Time" : 230,
        "Shape_Length" : 0.0027101020275711921
      },
      "geometry" : {
        "paths" : [
          [
            [
              76.897375000000068,
              43.26250200000004
            ],
            [
              76.899932000000035,
              43.263400000000047
            ]
          ]
        ]
      }
    },
    {
      "attributes" : {
        "OBJECTID_1" : 30,
        "Time" : 155,
        "Shape_Length" : 0.0018316489838346487
      },
      "geometry" : {
        "paths" : [
          [
            [
              76.899932000000035,
              43.263400000000047
            ],
            [
              76.901665000000037,
              43.263993000000028
            ]
          ]
        ]
      }
    },
    {
      "attributes" : {
        "OBJECTID_1" : 31,
        "Time" : 133,
        "Shape_Length" : 0.0015826815851917139
      },
      "geometry" : {
        "paths" : [
          [
            [
              76.901665000000037,
              43.263993000000028
            ],
            [
              76.903185000000065,
              43.264434000000051
            ]
          ]
        ]
      }
    },
    {
      "attributes" : {
        "OBJECTID_1" : 32,
        "Time" : 164,
        "Shape_Length" : 0.0019520435445791258
      },
      "geometry" : {
        "paths" : [
          [
            [
              76.903185000000065,
              43.264434000000051
            ],
            [
              76.905060000000049,
              43.264977000000044
            ]
          ]
        ]
      }
    },
    {
      "attributes" : {
        "OBJECTID_1" : 33,
        "Time" : 190,
        "Shape_Length" : 0.002310768270508432
      },
      "geometry" : {
        "paths" : [
          [
            [
              76.905060000000049,
              43.264977000000044
            ],
            [
              76.907335000000046,
              43.265382000000045
            ]
          ]
        ]
      }
    },
    {
      "attributes" : {
        "OBJECTID_1" : 34,
        "Time" : 163,
        "Shape_Length" : 0.001988335987712417
      },
      "geometry" : {
        "paths" : [
          [
            [
              76.907335000000046,
              43.265382000000045
            ],
            [
              76.909293000000048,
              43.265728000000081
            ]
          ]
        ]
      }
    },
    {
      "attributes" : {
        "OBJECTID_1" : 35,
        "Time" : 184,
        "Shape_Length" : 0.0022170363100457572
      },
      "geometry" : {
        "paths" : [
          [
            [
              76.909293000000048,
              43.265728000000081
            ],
            [
              76.911446000000069,
              43.266257000000053
            ]
          ]
        ]
      }
    },
    {
      "attributes" : {
        "OBJECTID_1" : 36,
        "Time" : 133,
        "Shape_Length" : 0.0015704330613002426
      },
      "geometry" : {
        "paths" : [
          [
            [
              76.911446000000069,
              43.266257000000053
            ],
            [
              76.912932000000069,
              43.266765000000078
            ]
          ]
        ]
      }
    },
    {
      "attributes" : {
        "OBJECTID_1" : 37,
        "Time" : 129,
        "Shape_Length" : 0.0015120449728515735
      },
      "geometry" : {
        "paths" : [
          [
            [
              76.912932000000069,
              43.266765000000078
            ],
            [
              76.91435400000006,
              43.26727900000003
            ]
          ]
        ]
      }
    },
    {
      "attributes" : {
        "OBJECTID_1" : 38,
        "Time" : 129,
        "Shape_Length" : 0.0015456924014538651
      },
      "geometry" : {
        "paths" : [
          [
            [
              76.91435400000006,
              43.26727900000003
            ],
            [
              76.915852000000029,
              43.267660000000035
            ]
          ]
        ]
      }
    },
    {
      "attributes" : {
        "OBJECTID_1" : 39,
        "Time" : 293,
        "Shape_Length" : 0.0035653858136327631
      },
      "geometry" : {
        "paths" : [
          [
            [
              76.915852000000029,
              43.267660000000035
            ],
            [
              76.919362000000035,
              43.268286000000046
            ]
          ]
        ]
      }
    },
    {
      "attributes" : {
        "OBJECTID_1" : 40,
        "Time" : 209,
        "Shape_Length" : 0.0025561934590659805
      },
      "geometry" : {
        "paths" : [
          [
            [
              76.919362000000035,
              43.268286000000046
            ],
            [
              76.921892000000071,
              43.268651000000034
            ]
          ]
        ]
      }
    },
    {
      "attributes" : {
        "OBJECTID_1" : 41,
        "Time" : 196,
        "Shape_Length" : 0.0024031339954349033
      },
      "geometry" : {
        "paths" : [
          [
            [
              76.921892000000071,
              43.268651000000034
            ],
            [
              76.92427900000007,
              43.268929000000071
            ]
          ]
        ]
      }
    },
    {
      "attributes" : {
        "OBJECTID_1" : 42,
        "Time" : 141,
        "Shape_Length" : 0.0017360659549752922
      },
      "geometry" : {
        "paths" : [
          [
            [
              76.92427900000007,
              43.268929000000071
            ],
            [
              76.926009000000079,
              43.269074000000046
            ]
          ]
        ]
      }
    },
    {
      "attributes" : {
        "OBJECTID_1" : 43,
        "Time" : 250,
        "Shape_Length" : 0.0030864079445258323
      },
      "geometry" : {
        "paths" : [
          [
            [
              76.926009000000079,
              43.269074000000046
            ],
            [
              76.929092000000082,
              43.269219000000078
            ]
          ]
        ]
      }
    },
    {
      "attributes" : {
        "OBJECTID_1" : 44,
        "Time" : 241,
        "Shape_Length" : 0.0029729302043187134
      },
      "geometry" : {
        "paths" : [
          [
            [
              76.929092000000082,
              43.269219000000078
            ],
            [
              76.932057000000043,
              43.269436000000042
            ]
          ]
        ]
      }
    },
    {
      "attributes" : {
        "OBJECTID_1" : 45,
        "Time" : 215,
        "Shape_Length" : 0.0026521593089580174
      },
      "geometry" : {
        "paths" : [
          [
            [
              76.932057000000043,
              43.269436000000042
            ],
            [
              76.93470700000006,
              43.269543000000056
            ]
          ]
        ]
      }
    },
    {
      "attributes" : {
        "OBJECTID_1" : 46,
        "Time" : 166,
        "Shape_Length" : 0.0020446623193301956
      },
      "geometry" : {
        "paths" : [
          [
            [
              76.93470700000006,
              43.269543000000056
            ],
            [
              76.936747000000082,
              43.269681000000048
            ]
          ]
        ]
      }
    },
    {
      "attributes" : {
        "OBJECTID_1" : 47,
        "Time" : 189,
        "Shape_Length" : 0.0023293323077492431
      },
      "geometry" : {
        "paths" : [
          [
            [
              76.936747000000082,
              43.269681000000048
            ],
            [
              76.939072000000067,
              43.269823000000031
            ]
          ]
        ]
      }
    },
    {
      "attributes" : {
        "OBJECTID_1" : 48,
        "Time" : 208,
        "Shape_Length" : 0.0025650452237361214
      },
      "geometry" : {
        "paths" : [
          [
            [
              76.939072000000067,
              43.269823000000031
            ],
            [
              76.941631000000029,
              43.269999000000041
            ]
          ]
        ]
      }
    },
    {
      "attributes" : {
        "OBJECTID_1" : 49,
        "Time" : 313,
        "Shape_Length" : 0.0038585247180819749
      },
      "geometry" : {
        "paths" : [
          [
            [
              76.941631000000029,
              43.269999000000041
            ],
            [
              76.945478000000037,
              43.270297000000028
            ]
          ]
        ]
      }
    },
    {
      "attributes" : {
        "OBJECTID_1" : 50,
        "Time" : 168,
        "Shape_Length" : 0.0020670292692873738
      },
      "geometry" : {
        "paths" : [
          [
            [
              76.945478000000037,
              43.270297000000028
            ],
            [
              76.947541000000058,
              43.270426000000043
            ]
          ]
        ]
      }
    },
    {
      "attributes" : {
        "OBJECTID_1" : 51,
        "Time" : 238,
        "Shape_Length" : 0.0029379572835420181
      },
      "geometry" : {
        "paths" : [
          [
            [
              76.947541000000058,
              43.270426000000043
            ],
            [
              76.950473000000045,
              43.270613000000026
            ]
          ]
        ]
      }
    },
    {
      "attributes" : {
        "OBJECTID_1" : 52,
        "Time" : 191,
        "Shape_Length" : 0.0023512807148528205
      },
      "geometry" : {
        "paths" : [
          [
            [
              76.950473000000045,
              43.270613000000026
            ],
            [
              76.952812000000051,
              43.270853000000045
            ]
          ]
        ]
      }
    },
    {
      "attributes" : {
        "OBJECTID_1" : 53,
        "Time" : 164,
        "Shape_Length" : 0.0020059992522693578
      },
      "geometry" : {
        "paths" : [
          [
            [
              76.952812000000051,
              43.270853000000045
            ],
            [
              76.954805000000079,
              43.271081000000038
            ]
          ]
        ]
      }
    },
    {
      "attributes" : {
        "OBJECTID_1" : 54,
        "Time" : 176,
        "Shape_Length" : 0.0021123079794040699
      },
      "geometry" : {
        "paths" : [
          [
            [
              76.954805000000079,
              43.271081000000038
            ],
            [
              76.956892000000039,
              43.271407000000067
            ]
          ]
        ]
      }
    },
    {
      "attributes" : {
        "OBJECTID_1" : 55,
        "Time" : 368,
        "Shape_Length" : 0.0045313261855832255
      },
      "geometry" : {
        "paths" : [
          [
            [
              76.956892000000039,
              43.271407000000067
            ],
            [
              76.961411000000055,
              43.271741000000077
            ]
          ]
        ]
      }
    },
    {
      "attributes" : {
        "OBJECTID_1" : 56,
        "Time" : 210,
        "Shape_Length" : 0.0025829603171832315
      },
      "geometry" : {
        "paths" : [
          [
            [
              76.961411000000055,
              43.271741000000077
            ],
            [
              76.963989000000083,
              43.271901000000071
            ]
          ]
        ]
      }
    },
    {
      "attributes" : {
        "OBJECTID_1" : 57,
        "Time" : 203,
        "Shape_Length" : 0.0025054742066126642
      },
      "geometry" : {
        "paths" : [
          [
            [
              76.960499000000084,
              43.27168400000005
            ],
            [
              76.958000000000084,
              43.27150400000005
            ]
          ]
        ]
      }
    },
    {
      "attributes" : {
        "OBJECTID_1" : 58,
        "Time" : 216,
        "Shape_Length" : 0.0026662874939239805
      },
      "geometry" : {
        "paths" : [
          [
            [
              76.958000000000084,
              43.27150400000005
            ],
            [
              76.955340000000035,
              43.271321000000057
            ]
          ]
        ]
      }
    },
    {
      "attributes" : {
        "OBJECTID_1" : 59,
        "Time" : 154,
        "Shape_Length" : 0.0018926787893927925
      },
      "geometry" : {
        "paths" : [
          [
            [
              76.955340000000035,
              43.271321000000057
            ],
            [
              76.953452000000084,
              43.271188000000052
            ]
          ]
        ]
      }
    },
    {
      "attributes" : {
        "OBJECTID_1" : 60,
        "Time" : 168,
        "Shape_Length" : 0.002065381562841181
      },
      "geometry" : {
        "paths" : [
          [
            [
              76.953452000000084,
              43.271188000000052
            ],
            [
              76.951392000000055,
              43.27103900000003
            ]
          ]
        ]
      }
    },
    {
      "attributes" : {
        "OBJECTID_1" : 61,
        "Time" : 236,
        "Shape_Length" : 0.002911661553137723
      },
      "geometry" : {
        "paths" : [
          [
            [
              76.951392000000055,
              43.27103900000003
            ],
            [
              76.948490000000049,
              43.27080200000006
            ]
          ]
        ]
      }
    },
    {
      "attributes" : {
        "OBJECTID_1" : 62,
        "Time" : 164,
        "Shape_Length" : 0.002019269669931479
      },
      "geometry" : {
        "paths" : [
          [
            [
              76.948490000000049,
              43.27080200000006
            ],
            [
              76.946477000000073,
              43.270643000000064
            ]
          ]
        ]
      }
    },
    {
      "attributes" : {
        "OBJECTID_1" : 63,
        "Time" : 189,
        "Shape_Length" : 0.0023244536992630517
      },
      "geometry" : {
        "paths" : [
          [
            [
              76.946477000000073,
              43.270643000000064
            ],
            [
              76.944160000000068,
              43.270457000000079
            ]
          ]
        ]
      }
    },
    {
      "attributes" : {
        "OBJECTID_1" : 64,
        "Time" : 179,
        "Shape_Length" : 0.0022006537665306145
      },
      "geometry" : {
        "paths" : [
          [
            [
              76.944160000000068,
              43.270457000000079
            ],
            [
              76.941966000000036,
              43.270286000000056
            ]
          ]
        ]
      }
    },
    {
      "attributes" : {
        "OBJECTID_1" : 65,
        "Time" : 173,
        "Shape_Length" : 0.0021342691957410903
      },
      "geometry" : {
        "paths" : [
          [
            [
              76.941966000000036,
              43.270286000000056
            ],
            [
              76.939839000000063,
              43.270110000000045
            ]
          ]
        ]
      }
    },
    {
      "attributes" : {
        "OBJECTID_1" : 66,
        "Time" : 145,
        "Shape_Length" : 0.0017890838437417136
      },
      "geometry" : {
        "paths" : [
          [
            [
              76.939839000000063,
              43.270110000000045
            ],
            [
              76.938053000000082,
              43.270005000000026
            ]
          ]
        ]
      }
    },
    {
      "attributes" : {
        "OBJECTID_1" : 67,
        "Time" : 194,
        "Shape_Length" : 0.0023972125479826607
      },
      "geometry" : {
        "paths" : [
          [
            [
              76.938053000000082,
              43.270005000000026
            ],
            [
              76.935661000000039,
              43.269847000000027
            ]
          ]
        ]
      }
    },
    {
      "attributes" : {
        "OBJECTID_1" : 68,
        "Time" : 201,
        "Shape_Length" : 0.0024731310114745253
      },
      "geometry" : {
        "paths" : [
          [
            [
              76.935661000000039,
              43.269847000000027
            ],
            [
              76.933202000000051,
              43.269583000000068
            ]
          ]
        ]
      }
    },
    {
      "attributes" : {
        "OBJECTID_1" : 69,
        "Time" : 225,
        "Shape_Length" : 0.0027721132733065034
      },
      "geometry" : {
        "paths" : [
          [
            [
              76.933202000000051,
              43.269583000000068
            ],
            [
              76.930436000000043,
              43.269399000000078
            ]
          ]
        ]
      }
    },
    {
      "attributes" : {
        "OBJECTID_1" : 70,
        "Time" : 199,
        "Shape_Length" : 0.002450619513479507
      },
      "geometry" : {
        "paths" : [
          [
            [
              76.930436000000043,
              43.269399000000078
            ],
            [
              76.927992000000074,
              43.269219000000078
            ]
          ]
        ]
      }
    },
    {
      "attributes" : {
        "OBJECTID_1" : 71,
        "Time" : 181,
        "Shape_Length" : 0.0022329755932311204
      },
      "geometry" : {
        "paths" : [
          [
            [
              76.927992000000074,
              43.269219000000078
            ],
            [
              76.925760000000082,
              43.269153000000074
            ]
          ]
        ]
      }
    },
    {
      "attributes" : {
        "OBJECTID_1" : 72,
        "Time" : 200,
        "Shape_Length" : 0.0024551547813001675
      },
      "geometry" : {
        "paths" : [
          [
            [
              76.925760000000082,
              43.269153000000074
            ],
            [
              76.923317000000054,
              43.268909000000065
            ]
          ]
        ]
      }
    },
    {
      "attributes" : {
        "OBJECTID_1" : 73,
        "Time" : 190,
        "Shape_Length" : 0.0023367158577814679
      },
      "geometry" : {
        "paths" : [
          [
            [
              76.923317000000054,
              43.268909000000065
            ],
            [
              76.920997000000057,
              43.26863000000003
            ]
          ]
        ]
      }
    },
    {
      "attributes" : {
        "OBJECTID_1" : 74,
        "Time" : 177,
        "Shape_Length" : 0.002166365620100111
      },
      "geometry" : {
        "paths" : [
          [
            [
              76.920997000000057,
              43.26863000000003
            ],
            [
              76.918855000000065,
              43.268306000000052
            ]
          ]
        ]
      }
    },
    {
      "attributes" : {
        "OBJECTID_1" : 75,
        "Time" : 188,
        "Shape_Length" : 0.0022940340014754581
      },
      "geometry" : {
        "paths" : [
          [
            [
              76.918855000000065,
              43.268306000000052
            ],
            [
              76.916599000000076,
              43.267890000000079
            ]
          ]
        ]
      }
    },
    {
      "attributes" : {
        "OBJECTID_1" : 76,
        "Time" : 188,
        "Shape_Length" : 0.0022735516268850725
      },
      "geometry" : {
        "paths" : [
          [
            [
              76.916599000000076,
              43.267890000000079
            ],
            [
              76.914378000000056,
              43.267404000000056
            ]
          ]
        ]
      }
    },
    {
      "attributes" : {
        "OBJECTID_1" : 77,
        "Time" : 141,
        "Shape_Length" : 0.0016681201994827421
      },
      "geometry" : {
        "paths" : [
          [
            [
              76.914378000000056,
              43.267404000000056
            ],
            [
              76.912793000000079,
              43.266884000000061
            ]
          ]
        ]
      }
    },
    {
      "attributes" : {
        "OBJECTID_1" : 78,
        "Time" : 149,
        "Shape_Length" : 0.0017640011337912121
      },
      "geometry" : {
        "paths" : [
          [
            [
              76.912793000000079,
              43.266884000000061
            ],
            [
              76.911125000000084,
              43.266310000000033
            ]
          ]
        ]
      }
    },
    {
      "attributes" : {
        "OBJECTID_1" : 79,
        "Time" : 177,
        "Shape_Length" : 0.0021289783935177732
      },
      "geometry" : {
        "paths" : [
          [
            [
              76.911125000000084,
              43.266310000000033
            ],
            [
              76.909060000000068,
              43.265792000000033
            ]
          ]
        ]
      }
    },
    {
      "attributes" : {
        "OBJECTID_1" : 80,
        "Time" : 197,
        "Shape_Length" : 0.0023976248664064545
      },
      "geometry" : {
        "paths" : [
          [
            [
              76.909060000000068,
              43.265792000000033
            ],
            [
              76.906697000000065,
              43.265386000000035
            ]
          ]
        ]
      }
    },
    {
      "attributes" : {
        "OBJECTID_1" : 81,
        "Time" : 171,
        "Shape_Length" : 0.0020614958161729318
      },
      "geometry" : {
        "paths" : [
          [
            [
              76.906697000000065,
              43.265386000000035
            ],
            [
              76.904680000000042,
              43.264960000000031
            ]
          ]
        ]
      }
    },
    {
      "attributes" : {
        "OBJECTID_1" : 82,
        "Time" : 206,
        "Shape_Length" : 0.00246711998087156
      },
      "geometry" : {
        "paths" : [
          [
            [
              76.904680000000042,
              43.264960000000031
            ],
            [
              76.902296000000035,
              43.264325000000042
            ]
          ]
        ]
      }
    },
    {
      "attributes" : {
        "OBJECTID_1" : 83,
        "Time" : 163,
        "Shape_Length" : 0.001914293603399138
      },
      "geometry" : {
        "paths" : [
          [
            [
              76.902296000000035,
              43.264325000000042
            ],
            [
              76.900494000000037,
              43.263679000000025
            ]
          ]
        ]
      }
    },
    {
      "attributes" : {
        "OBJECTID_1" : 84,
        "Time" : 152,
        "Shape_Length" : 0.0018192064203710189
      },
      "geometry" : {
        "paths" : [
          [
            [
              76.900494000000037,
              43.263679000000025
            ],
            [
              76.898708000000056,
              43.263333000000046
            ]
          ]
        ]
      }
    },
    {
      "attributes" : {
        "OBJECTID_1" : 85,
        "Time" : 132,
        "Shape_Length" : 0.0015698165497718319
      },
      "geometry" : {
        "paths" : [
          [
            [
              76.898708000000056,
              43.263333000000046
            ],
            [
              76.89719000000008,
              43.262933000000032
            ]
          ]
        ]
      }
    },
    {
      "attributes" : {
        "OBJECTID_1" : 86,
        "Time" : 213,
        "Shape_Length" : 0.0025113581982541115
      },
      "geometry" : {
        "paths" : [
          [
            [
              76.89719000000008,
              43.262933000000032
            ],
            [
              76.894824000000085,
              43.262091000000055
            ]
          ]
        ]
      }
    },
    {
      "attributes" : {
        "OBJECTID_1" : 87,
        "Time" : 548,
        "Shape_Length" : 0.0064240380603266091
      },
      "geometry" : {
        "paths" : [
          [
            [
              76.894824000000085,
              43.262091000000055
            ],
            [
              76.88880800000004,
              43.259838000000059
            ]
          ]
        ]
      }
    },
    {
      "attributes" : {
        "OBJECTID_1" : 88,
        "Time" : 306,
        "Shape_Length" : 0.00362904464009195
      },
      "geometry" : {
        "paths" : [
          [
            [
              76.88880800000004,
              43.259838000000059
            ],
            [
              76.885350000000074,
              43.258737000000053
            ]
          ]
        ]
      }
    },
    {
      "attributes" : {
        "OBJECTID_1" : 89,
        "Time" : 181,
        "Shape_Length" : 0.0021695679293722552
      },
      "geometry" : {
        "paths" : [
          [
            [
              76.885350000000074,
              43.258737000000053
            ],
            [
              76.883250000000032,
              43.258192000000065
            ]
          ]
        ]
      }
    },
    {
      "attributes" : {
        "OBJECTID_1" : 90,
        "Time" : 167,
        "Shape_Length" : 0.0020525033495362175
      },
      "geometry" : {
        "paths" : [
          [
            [
              76.883250000000032,
              43.258192000000065
            ],
            [
              76.881209000000069,
              43.257975000000044
            ]
          ]
        ]
      }
    },
    {
      "attributes" : {
        "OBJECTID_1" : 91,
        "Time" : 536,
        "Shape_Length" : 0.0066201368566007951
      },
      "geometry" : {
        "paths" : [
          [
            [
              76.881209000000069,
              43.257975000000044
            ],
            [
              76.874593000000061,
              43.258209000000079
            ]
          ]
        ]
      }
    },
    {
      "attributes" : {
        "OBJECTID_1" : 92,
        "Time" : 417,
        "Shape_Length" : 0.0051185495015501096
      },
      "geometry" : {
        "paths" : [
          [
            [
              76.874593000000061,
              43.258209000000079
            ],
            [
              76.869475000000079,
              43.258134000000041
            ]
          ]
        ]
      }
    },
    {
      "attributes" : {
        "OBJECTID_1" : 93,
        "Time" : 359,
        "Shape_Length" : 0.0042708558861440154
      },
      "geometry" : {
        "paths" : [
          [
            [
              76.869475000000079,
              43.258134000000041
            ],
            [
              76.865386000000058,
              43.256901000000028
            ]
          ]
        ]
      }
    },
    {
      "attributes" : {
        "OBJECTID_1" : 94,
        "Time" : 172,
        "Shape_Length" : 0.0019691099512137268
      },
      "geometry" : {
        "paths" : [
          [
            [
              76.865386000000058,
              43.256901000000028
            ],
            [
              76.863581000000067,
              43.256114000000025
            ]
          ]
        ]
      }
    },
    {
      "attributes" : {
        "OBJECTID_1" : 95,
        "Time" : 158,
        "Shape_Length" : 0.0017145392967136386
      },
      "geometry" : {
        "paths" : [
          [
            [
              76.863581000000067,
              43.256114000000025
            ],
            [
              76.86218400000007,
              43.255120000000034
            ]
          ]
        ]
      }
    },
    {
      "attributes" : {
        "OBJECTID_1" : 96,
        "Time" : 175,
        "Shape_Length" : 0.0018834938279784965
      },
      "geometry" : {
        "paths" : [
          [
            [
              76.86218400000007,
              43.255120000000034
            ],
            [
              76.860666000000037,
              43.254005000000063
            ]
          ]
        ]
      }
    },
    {
      "attributes" : {
        "OBJECTID_1" : 97,
        "Time" : 308,
        "Shape_Length" : 0.0034087619453226007
      },
      "geometry" : {
        "paths" : [
          [
            [
              76.860666000000037,
              43.254005000000063
            ],
            [
              76.857733000000053,
              43.252268000000072
            ]
          ]
        ]
      }
    },
    {
      "attributes" : {
        "OBJECTID_1" : 98,
        "Time" : 180,
        "Shape_Length" : 0.0021547791070025434
      },
      "geometry" : {
        "paths" : [
          [
            [
              76.857733000000053,
              43.252268000000072
            ],
            [
              76.855660000000057,
              43.251680000000079
            ]
          ]
        ]
      }
    },
    {
      "attributes" : {
        "OBJECTID_1" : 99,
        "Time" : 174,
        "Shape_Length" : 0.0020945417159766448
      },
      "geometry" : {
        "paths" : [
          [
            [
              76.855660000000057,
              43.251680000000079
            ],
            [
              76.853627000000074,
              43.251176000000044
            ]
          ]
        ]
      }
    },
    {
      "attributes" : {
        "OBJECTID_1" : 100,
        "Time" : 214,
        "Shape_Length" : 0.0025701511628741036
      },
      "geometry" : {
        "paths" : [
          [
            [
              76.853627000000074,
              43.251176000000044
            ],
            [
              76.851133000000061,
              43.250555000000077
            ]
          ]
        ]
      }
    },
    {
      "attributes" : {
        "OBJECTID_1" : 101,
        "Time" : 324,
        "Shape_Length" : 0.0039034514215286029
      },
      "geometry" : {
        "paths" : [
          [
            [
              76.851133000000061,
              43.250555000000077
            ],
            [
              76.847340000000031,
              43.249633000000074
            ]
          ]
        ]
      }
    },
    {
      "attributes" : {
        "OBJECTID_1" : 102,
        "Time" : 314,
        "Shape_Length" : 0.0036936499563299955
      },
      "geometry" : {
        "paths" : [
          [
            [
              76.847340000000031,
              43.249633000000074
            ],
            [
              76.843845000000044,
              43.248438000000078
            ]
          ]
        ]
      }
    },
    {
      "attributes" : {
        "OBJECTID_1" : 103,
        "Time" : 195,
        "Shape_Length" : 0.0022428956729910001
      },
      "geometry" : {
        "paths" : [
          [
            [
              76.843845000000044,
              43.248438000000078
            ],
            [
              76.841804000000081,
              43.247508000000039
            ]
          ]
        ]
      }
    },
    {
      "attributes" : {
        "OBJECTID_1" : 104,
        "Time" : 291,
        "Shape_Length" : 0.0033984728923671928
      },
      "geometry" : {
        "paths" : [
          [
            [
              76.841804000000081,
              43.247508000000039
            ],
            [
              76.838641000000052,
              43.246265000000051
            ]
          ]
        ]
      }
    },
    {
      "attributes" : {
        "OBJECTID_1" : 105,
        "Time" : 378,
        "Shape_Length" : 0.0044546040227872487
      },
      "geometry" : {
        "paths" : [
          [
            [
              76.838641000000052,
              43.246265000000051
            ],
            [
              76.834357000000068,
              43.245044000000064
            ]
          ]
        ]
      }
    },
    {
      "attributes" : {
        "OBJECTID_1" : 106,
        "Time" : 326,
        "Shape_Length" : 0.0039110676291747659
      },
      "geometry" : {
        "paths" : [
          [
            [
              76.834357000000068,
              43.245044000000064
            ],
            [
              76.830572000000075,
              43.24405900000005
            ]
          ]
        ]
      }
    },
    {
      "attributes" : {
        "OBJECTID_1" : 107,
        "Time" : 320,
        "Shape_Length" : 0.0038505090572525966
      },
      "geometry" : {
        "paths" : [
          [
            [
              76.830572000000075,
              43.24405900000005
            ],
            [
              76.826834000000076,
              43.243135000000052
            ]
          ]
        ]
      }
    }
  ]
}